Get.py
MANIFEST.in
Send.py
__init__.py
setup.py
testing.py
All_Proxy.egg-info/PKG-INFO
All_Proxy.egg-info/SOURCES.txt
All_Proxy.egg-info/dependency_links.txt
All_Proxy.egg-info/requires.txt
All_Proxy.egg-info/top_level.txt