Metadata-Version: 2.1
Name: All-Proxy
Version: 1.2
Summary: Easily get a working Proxy list
Author: TheescapedShadow
Requires-Dist: requests
Requires-Dist: beautifulsoup4
Requires-Dist: tqdm
